simplemailproxy/__init__.py
simplemailproxy/__main__.py
simplemailproxy-1.0.0.dist-info/METADATA
simplemailproxy-1.0.0.dist-info/WHEEL
simplemailproxy-1.0.0.dist-info/top_level.txt
simplemailproxy-1.0.0.dist-info/RECORD
