Metadata-Version: 2.1
Name: simplemailproxy
Version: 1.0.0
Summary: Simple Mail Proxy
Home-page: https://github.com/ondrejsika/python-simplemailproxy
Author: Ondrej Sika
Author-email: ondrej@ondrejsika.com
License: UNKNOWN
Platform: UNKNOWN
